README.txt
setup.py
docs/HISTORY.txt
docs/LICENSE.GPL
docs/LICENSE.txt
experimental/__init__.py
experimental.opaquespeedup.egg-info/PKG-INFO
experimental.opaquespeedup.egg-info/SOURCES.txt
experimental.opaquespeedup.egg-info/dependency_links.txt
experimental.opaquespeedup.egg-info/namespace_packages.txt
experimental.opaquespeedup.egg-info/not-zip-safe
experimental.opaquespeedup.egg-info/requires.txt
experimental.opaquespeedup.egg-info/top_level.txt
experimental/opaquespeedup/__init__.py
experimental/opaquespeedup/configure.zcml
experimental/opaquespeedup/monkey.py