Metadata-Version: 1.0
Name: experimental.opaquespeedup
Version: 1.0
Summary: Plone-specific optimization of looking up CMF's "opaque items"
Home-page: http://www.jarn.com/
Author: Jarn AS
Author-email: info@jarn.com
License: GPL
Download-URL: http://pypi.python.org/pypi/experimental.opaquespeedup/
Keywords: plone events opaque optimization
Platform: Any
Classifier: Environment :: Web Environment
Classifier: Framework :: Plone
Classifier: Intended Audience :: Developers
Classifier: Intended Audience :: System Administrators
Classifier: Intended Audience :: Other Audience
Classifier: License :: OSI Approved :: GNU General Public License (GPL)
Classifier: Operating System :: OS Independent
Classifier: Programming Language :: Python
